django_polls_dixonogb/__init__.py
django_polls_dixonogb/admin.py
django_polls_dixonogb/apps.py
django_polls_dixonogb/models.py
django_polls_dixonogb/tests.py
django_polls_dixonogb/urls.py
django_polls_dixonogb/views.py
django_polls_dixonogb/migrations/0001_initial.py
django_polls_dixonogb/migrations/__init__.py
django_polls_dixonogb/static/polls/style.css
django_polls_dixonogb/static/polls/images/background.png
django_polls_dixonogb/templates/polls/detail.html
django_polls_dixonogb/templates/polls/index.html
django_polls_dixonogb/templates/polls/results.html
django_polls_dixonogb-0.1.dist-info/licenses/LICENSE
django_polls_dixonogb-0.1.dist-info/METADATA
django_polls_dixonogb-0.1.dist-info/WHEEL
django_polls_dixonogb-0.1.dist-info/top_level.txt
django_polls_dixonogb-0.1.dist-info/RECORD
